exotic_miri/reference/__init__.py
exotic_miri/reference/get_default_gain.py
exotic_miri/reference/get_default_readnoise.py
exotic_miri/reference/get_integration_times.py
exotic_miri/reference/get_wavelength_map.py
exotic_miri/reference/set_custom_gain.py
exotic_miri/reference/set_custom_linearity.py
exotic_miri/stage_1/__init__.py
exotic_miri/stage_1/drop_groups_step.py
exotic_miri/stage_1/drop_integrations_step.py
exotic_miri/stage_1/group_level_background_subtract_step.py
exotic_miri/stage_1/reference_pixel_step.py
exotic_miri/stage_1/regroup_step.py
exotic_miri/stage_2/__init__.py
exotic_miri/stage_2/align_spectra_step.py
exotic_miri/stage_2/background_subtract_step.py
exotic_miri/stage_2/clean_outliers_step.py
exotic_miri/stage_2/extract_1d_box_step.py
exotic_miri/stage_2/extract_1d_optimal_step.py
exotic_miri/stage_2/inspect_dq_flags.py
exotic_miri-1.0.1.dist-info/LICENSE
exotic_miri-1.0.1.dist-info/METADATA
exotic_miri-1.0.1.dist-info/WHEEL
exotic_miri-1.0.1.dist-info/top_level.txt
exotic_miri-1.0.1.dist-info/RECORD
