Metadata-Version: 2.1
Name: exotic-miri
Version: 1.0.1
Summary: ExoTiC MIRI data reduction steps
Home-page: https://github.com/Exo-TiC/ExoTiC-MIRI
Author: David Grant
Author-email: david.grant@bristol.ac.uk
License: MIT
Classifier: Intended Audience :: Science/Research
Classifier: License :: OSI Approved :: MIT License
Classifier: Operating System :: OS Independent
Classifier: Programming Language :: Python
Classifier: Programming Language :: Python :: 3
Classifier: Topic :: Scientific/Engineering :: Astronomy
Classifier: Topic :: Software Development :: Libraries :: Python Modules
Requires-Python: >=3.8
License-File: LICENSE
Requires-Dist: jwst (>=1.8.2)
Requires-Dist: numpy
Requires-Dist: astropy
Requires-Dist: scipy
Requires-Dist: matplotlib
